pyarrowfs_adlgen2/__init__.py
pyarrowfs_adlgen2/core.py
pyarrowfs_adlgen2-0.2.5.dist-info/LICENSE.txt
pyarrowfs_adlgen2-0.2.5.dist-info/METADATA
pyarrowfs_adlgen2-0.2.5.dist-info/WHEEL
pyarrowfs_adlgen2-0.2.5.dist-info/top_level.txt
pyarrowfs_adlgen2-0.2.5.dist-info/RECORD
