Metadata-Version: 2.1
Name: pyarrowfs-adlgen2
Version: 0.2.5
Summary: Use pyarrow with Azure Data Lake gen2
Home-page: https://github.com/kaaveland/pyarrowfs-adlgen2
Author: Robin Kåveland
Author-email: kaaveland@gmail.com
License: MIT
Keywords: azure datalake filesystem pyarrow parquet
Classifier: Development Status :: 3 - Alpha
Classifier: License :: OSI Approved :: MIT License
Classifier: Programming Language :: Python :: 3 :: Only
Classifier: Programming Language :: Python :: 3.6
Classifier: Programming Language :: Python :: 3.7
Classifier: Programming Language :: Python :: 3.8
Classifier: Programming Language :: Python :: 3.9
Classifier: Programming Language :: Python :: 3.10
Classifier: Programming Language :: Python :: 3.11
Requires-Python: >=3.6
License-File: LICENSE.txt
Requires-Dist: pyarrow >=1.0.0
Requires-Dist: azure-storage-file-datalake
Provides-Extra: dev
Requires-Dist: pandas ; extra == 'dev'
Requires-Dist: pytest ; extra == 'dev'
